rtl/router/sequential/memory/miso_fifo.sv
// Multiple Input Single Output (MISO) FIFO
module miso_fifo #(
    parameter int DEPTH = 32,  
    parameter int DATA_WIDTH = 8,
    parameter int DATA_LENGTH = 9,
    localparam ADDR_WIDTH = $clog2(DEPTH),
    parameter int INDEX = 0
)(
    input logic i_clk, i_nrst, i_clear, i_write_en, i_pop_en, i_r_pointer_reset,
    input logic [DATA_LENGTH-1:0][DATA_WIDTH-1:0] i_data,       
    input logic [DATA_LENGTH-1:0] i_valid,
    output logic [DATA_WIDTH-1:0] o_data,                          
    output logic o_empty, o_full, o_pop_valid       
);
    logic [ADDR_WIDTH-1:0] w_pointer, r_pointer;
    logic [DATA_WIDTH-1:0] fifo [DEPTH-1:0];

    logic write_en;
    assign write_en = i_write_en & !o_full;

    // Write data
    always @ (posedge i_clk or negedge i_nrst) begin
        if (~i_nrst) begin
            w_pointer <= 0;
        end else if (i_clear) begin
            w_pointer <= 0;
        end else if (write_en) begin
            for (int i = 0; i < DATA_LENGTH; i = i + 1) begin
                if (i_valid[i] == 1) begin
                    fifo[w_pointer + i] <= i_data[i];
                    w_pointer <= w_pointer + i + 1;
                end 
            end
        end
    end

    // Pop data
    always_ff @ (posedge i_clk or negedge i_nrst) begin
        if (~i_nrst || i_r_pointer_reset) begin
            r_pointer <= 0;
            o_data <= 0;
            o_pop_valid <= 0;
        end else if (i_clear) begin
            r_pointer <= 0;
            o_data <= 0;
            o_pop_valid <= 0;
        end else if (i_pop_en && !o_empty) begin
            o_data <= fifo[r_pointer];
            r_pointer <= r_pointer + 1;
            o_pop_valid <= 1;
        end else begin
            o_data <= 0;
            o_pop_valid <= 0;
        end
    end

    // Status signals
    always_comb begin
        o_full = (w_pointer + 1) == r_pointer;
        o_empty = (w_pointer == r_pointer);
    end
endmodule

rtl/router/sequential/sram.sv
module sram # (
    parameter int ADDR_WIDTH = 8,
    parameter int DATA_WIDTH = 64
) (
    input logic i_clk, i_nrst, i_write_en, i_read_en,
    input logic [DATA_WIDTH-1:0] i_data_in,
    input logic [ADDR_WIDTH-1:0] i_write_addr, i_read_addr,
    output logic [DATA_WIDTH-1:0] o_data_out,
    output logic o_data_out_valid
);
    localparam DEPTH = ADDR_WIDTH * ADDR_WIDTH;
    logic [DATA_WIDTH-1:0] buffer [DEPTH-1:0];
    logic [DATA_WIDTH-1:0] reg_data_out;

    // initial begin
    //     $monitor("[%0t] [BUFFER] writeEn=%0b dataIn=0x%0h readEn=%0b dataOut=0x%0h",
    //         $time, i_write_en, i_data_in, i_read_en, o_data_out);
    // end

    // Read data
    always_ff @(posedge i_clk or negedge i_nrst) begin
        if (~i_nrst) begin
            o_data_out_valid <= 0;
        end else begin
            if (i_read_en) begin
                reg_data_out <= buffer[i_read_addr];
                o_data_out_valid <= 1;
            end else begin
                o_data_out_valid <= 0;
            end
        end
    end

    assign o_data_out = reg_data_out;

    // Write data
    always_ff @(posedge i_clk) begin
        if (i_write_en) begin
            buffer[i_write_addr] <= i_data_in;
        end
    end

endmodule

rtl/router/sequential/weight_top.sv
/*
    interface for writing to SRAM
    interface for controling weight router
*/

module weight_top (
    input logic i_clk, i_nrst, i_reg_clear, i_fifo_clear,
    input logic i_sram_write_en, i_route_en, i_data_out_en, i_route_reuse,

    input logic [SRAM_DATA_WIDTH-1:0] i_data_in,
    input logic [ADDR_WIDTH-1:0] i_write_addr,

    // Control parameters
    input logic [ADDR_WIDTH-1:0] i_start_addr, i_addr_offset,
    input logic [ADDR_WIDTH-1:0] i_route_size, // 9 for 3x3 kernel and x depending on number of channels
    output logic o_route_ready, o_route_done,

    // Output signals
    output logic [DATA_WIDTH-1:0] o_data,
    output logic o_data_valid
);
    localparam int SRAM_DATA_WIDTH = 64;
    localparam int ADDR_WIDTH = 8;
    localparam int DATA_WIDTH = 8;
    localparam int DATA_LENGTH = 8;

    // MISO FIFO Params
    localparam int DEPTH = 32;
    localparam int FIFO_ADDR = $clog2(DEPTH);

    // SRAM
    logic sram_data_out_valid;
    logic [SRAM_DATA_WIDTH-1:0] sram_data_out;
    sram #(
        .ADDR_WIDTH(ADDR_WIDTH),
        .DATA_WIDTH(SRAM_DATA_WIDTH)
    ) weight_sram (
        .i_clk(i_clk),
        .i_write_en(i_sram_write_en),
        .i_read_en(sram_read_en),
        .i_data_in(i_data_in),
        .i_write_addr(i_write_addr),
        .i_read_addr(sram_read_addr),
        .o_data_out(sram_data_out),
        .o_data_out_valid(sram_data_out_valid)
    );

    // MISO FIFO
    miso_fifo #(
        .DEPTH(DEPTH),
        .DATA_WIDTH(DATA_WIDTH),
        .DATA_LENGTH(DATA_LENGTH)
    ) fifo_inst (
        .i_clk(i_clk),
        .i_nrst(i_nrst),
        .i_clear(i_fifo_clear || i_reg_clear),
        .i_write_en(sram_data_out_valid),
        .i_pop_en(fifo_pop_en),
        .i_r_pointer_reset(i_route_reuse),
        .i_data(sram_data_out),
        .i_valid({DATA_LENGTH{sram_data_out_valid}}),
        .o_data(o_data),
        .o_empty(),
        .o_full(),
        .o_pop_valid(o_data_valid)
    );

    // Controller
    // Read from SRAM and write to MISO FIFO
    logic [ADDR_WIDTH-1:0] read_counter, sram_read_addr; 
    logic sram_read_en, read_en, sram_read_done;
    assign sram_read_done = read_counter > i_addr_offset;
    assign read_en = i_route_en & ~sram_read_done;

    always_ff @(posedge i_clk or negedge i_nrst) begin
        if (~i_nrst) begin
            sram_read_en <= 0;
            read_counter <= 0;
            sram_read_addr <= 0;
        end else begin
            if (i_reg_clear) begin
                sram_read_en <= 0;
                sram_read_addr <= 0;
                read_counter <= 0;
            end else if (read_en) begin
                sram_read_en <= 1;
                sram_read_addr <= i_start_addr + read_counter;
                read_counter <= read_counter + 1;
            end else begin
                sram_read_en <= 0;
                sram_read_addr <= 0;
            end
        end
    end

    logic [FIFO_ADDR-1:0] fifo_r_pointer;
    logic fifo_pop_en;

    // assign fifo_pop_en = i_data_out_en & sram_read_done;
    assign o_route_ready = sram_read_done;

    // Read from MISO FIFO and handle reuse 
    always_ff @(posedge i_clk or negedge i_nrst) begin
        if (~i_nrst) begin
            fifo_r_pointer <= 0;
            o_route_done <= 0;
        end else begin
            if (i_reg_clear || i_route_reuse) begin
                fifo_r_pointer <= 0;
                fifo_pop_en <= 0;
                o_route_done <= 0;
            end else if (i_data_out_en & sram_read_done) begin
                if (fifo_r_pointer < i_route_size) begin
                    fifo_pop_en <= 1;
                    fifo_r_pointer <= fifo_r_pointer + 1;
                end else begin
                    fifo_pop_en <= 0;
                    o_route_done <= 1;
                end
            end
        end
    end

endmodule

rtl/router/sequential/tb_weight_top.sv
`timescale 1ns/1ps

module weight_top_tb;

    // Parameters
    localparam int SRAM_DATA_WIDTH = 64;
    localparam int ADDR_WIDTH = 8;
    localparam int DATA_WIDTH = 8;
    localparam int DATA_LENGTH = 8;

    // Testbench signals
    logic clk, nrst;
    logic en, reg_clear;
    logic sram_write_en, route_en, data_out_en, route_reuse;

    logic [SRAM_DATA_WIDTH-1:0] data_in;
    logic [ADDR_WIDTH-1:0] write_addr;

    logic [ADDR_WIDTH-1:0] start_addr, addr_offset;
    logic [ADDR_WIDTH-1:0] route_size;
    logic route_ready;

    logic [DATA_WIDTH-1:0] data_out;
    logic data_valid;
            integer file, r;
                    reg [SRAM_DATA_WIDTH-1:0] mem_data;

    // DUT instantiation
    weight_top dut (
        .i_clk(clk),
        .i_nrst(nrst),
        .i_reg_clear(reg_clear),
        .i_fifo_clear(),
        .i_route_reuse(route_reuse),
        .i_sram_write_en(sram_write_en),
        .i_route_en(route_en),
        .i_data_out_en(data_out_en),
        .i_data_in(data_in),
        .i_write_addr(write_addr),
        .i_start_addr(start_addr),
        .i_addr_offset(addr_offset),
        .i_route_size(route_size),
        .o_route_ready(route_ready),
        .o_route_done(),
        .o_data(data_out),
        .o_data_valid(data_valid)
    );

    // Clock generation
    initial clk = 0;
    always #5 clk = ~clk; // 10 ns clock period

    // Testbench logic
    initial begin
        $dumpfile("tb.vcd");
        $dumpvars();
        // Initialize signals
        nrst = 0;
        en = 0;
        reg_clear = 0;
        sram_write_en = 0;
        route_en = 0;
        data_in = 0;
        data_out_en = 0;
        write_addr = 0;
        start_addr = 8'h00;
        addr_offset = 8'd1;
        route_reuse = 0;
        route_size = 8'h09;

        // Reset the DUT
        #10 nrst = 1;

        // Clear registers
        reg_clear = 1;
        #10 reg_clear = 0;

        // Open and read the .mem file


        file = $fopen("sram.mem", "r");
        if (file == 0) begin
            $display("Error opening file!");
            $finish;
        end

        // Write data to SRAM
        while (!$feof(file)) begin
            r = $fscanf(file, "%h\n", mem_data);
            if (r != 1) begin
                $display("Error reading data from file!");
                $finish;
            end
            sram_write_en = 1;
            data_in = mem_data;
            #10; // Wait for one clock cycle
            write_addr = write_addr + 1;
        end
        sram_write_en = 0;
        $fclose(file);

        // Enable routing
        #10;
        route_en = 1;
        #50;
        route_en = 0;
        data_out_en = 1;

        // End simulation
        #100;

        route_reuse = 1;
        #10;
        route_reuse = 0;
        #150;
        $finish;
    end

    // Monitor outputs
    initial begin
        $monitor("Time: %0t | Route Ready: %b | Data Out: %h | Data Valid: %b", 
                 $time, route_ready, data_out, data_valid);
    end

endmodule

rtl/router/sequential/tb.vcd
$date
	Thu Jan 23 00:56:43 2025
$end
$version
	Icarus Verilog
$end
$timescale
	1ps
$end
$scope module weight_top_tb $end
$var wire 1 ! route_ready $end
$var wire 1 " data_valid $end
$var wire 8 # data_out [7:0] $end
$var parameter 32 $ ADDR_WIDTH $end
$var parameter 32 % DATA_LENGTH $end
$var parameter 32 & DATA_WIDTH $end
$var parameter 32 ' SRAM_DATA_WIDTH $end
$var reg 8 ( addr_offset [7:0] $end
$var reg 1 ) clk $end
$var reg 64 * data_in [63:0] $end
$var reg 1 + data_out_en $end
$var reg 1 , en $end
$var reg 64 - mem_data [63:0] $end
$var reg 1 . nrst $end
$var reg 1 / reg_clear $end
$var reg 1 0 route_en $end
$var reg 1 1 route_reuse $end
$var reg 8 2 route_size [7:0] $end
$var reg 1 3 sram_write_en $end
$var reg 8 4 start_addr [7:0] $end
$var reg 8 5 write_addr [7:0] $end
$var integer 32 6 file [31:0] $end
$var integer 32 7 r [31:0] $end
$scope module dut $end
$var wire 8 8 i_addr_offset [7:0] $end
$var wire 1 ) i_clk $end
$var wire 64 9 i_data_in [63:0] $end
$var wire 1 + i_data_out_en $end
$var wire 1 : i_fifo_clear $end
$var wire 1 . i_nrst $end
$var wire 1 / i_reg_clear $end
$var wire 1 0 i_route_en $end
$var wire 1 1 i_route_reuse $end
$var wire 8 ; i_route_size [7:0] $end
$var wire 1 3 i_sram_write_en $end
$var wire 8 < i_start_addr [7:0] $end
$var wire 8 = i_write_addr [7:0] $end
$var wire 1 ! o_route_ready $end
$var wire 1 > read_en $end
$var wire 1 ? sram_read_done $end
$var wire 1 @ sram_data_out_valid $end
$var wire 64 A sram_data_out [63:0] $end
$var wire 1 " o_data_valid $end
$var wire 8 B o_data [7:0] $end
$var parameter 32 C ADDR_WIDTH $end
$var parameter 32 D DATA_LENGTH $end
$var parameter 32 E DATA_WIDTH $end
$var parameter 32 F DEPTH $end
$var parameter 32 G FIFO_ADDR $end
$var parameter 32 H SRAM_DATA_WIDTH $end
$var reg 1 I fifo_pop_en $end
$var reg 5 J fifo_r_pointer [4:0] $end
$var reg 1 K o_route_done $end
$var reg 8 L read_counter [7:0] $end
$var reg 8 M sram_read_addr [7:0] $end
$var reg 1 N sram_read_en $end
$scope module fifo_inst $end
$var wire 1 O i_clear $end
$var wire 1 ) i_clk $end
$var wire 1 . i_nrst $end
$var wire 1 I i_pop_en $end
$var wire 1 1 i_r_pointer_reset $end
$var wire 8 P i_valid [7:0] $end
$var wire 1 Q write_en $end
$var wire 1 @ i_write_en $end
$var wire 64 R i_data [63:0] $end
$var parameter 32 S ADDR_WIDTH $end
$var parameter 32 T DATA_LENGTH $end
$var parameter 32 U DATA_WIDTH $end
$var parameter 32 V DEPTH $end
$var parameter 32 W INDEX $end
$var reg 8 X o_data [7:0] $end
$var reg 1 Y o_empty $end
$var reg 1 Z o_full $end
$var reg 1 " o_pop_valid $end
$var reg 5 [ r_pointer [4:0] $end
$var reg 5 \ w_pointer [4:0] $end
$scope begin $ivl_for_loop0 $end
$var integer 32 ] i [31:0] $end
$upscope $end
$upscope $end
$scope module weight_sram $end
$var wire 1 ) i_clk $end
$var wire 64 ^ i_data_in [63:0] $end
$var wire 1 _ i_nrst $end
$var wire 8 ` i_read_addr [7:0] $end
$var wire 1 N i_read_en $end
$var wire 8 a i_write_addr [7:0] $end
$var wire 1 3 i_write_en $end
$var wire 64 b o_data_out [63:0] $end
$var parameter 32 c ADDR_WIDTH $end
$var parameter 32 d DATA_WIDTH $end
$var parameter 64 e DEPTH $end
$var reg 1 @ o_data_out_valid $end
$var reg 64 f reg_data_out [63:0] $end
$upscope $end
$upscope $end
$upscope $end
$enddefinitions $end
$comment Show the parameter values. $end
$dumpall
b1000000 e
b1000000 d
b1000 c
b0 W
b100000 V
b1000 U
b1000 T
b101 S
b1000000 H
b101 G
b100000 F
b1000 E
b1000 D
b1000 C
b1000000 '
b1000 &
b1000 %
b1000 $
$end
#0
$dumpvars
bx f
bx b
b0 a
b0 `
z_
b0 ^
b0 ]
b0 \
b0 [
0Z
1Y
b0 X
bx R
xQ
bx P
xO
0N
b0 M
b0 L
0K
b0 J
xI
b0 B
bx A
x@
0?
0>
b0 =
b0 <
b1001 ;
z:
b0 9
b1 8
bx 7
bx 6
b0 5
b0 4
03
b1001 2
01
00
0/
0.
bx -
0,
0+
b0 *
0)
b1 (
b0 #
0"
0!
$end
#5000
0Q
b0 P
0@
1)
#10000
1O
0)
1/
1.
#15000
0I
1)
#20000
xO
0)
b11100000110000001010000010000000011000000100000000100000000 *
b11100000110000001010000010000000011000000100000000100000000 9
b11100000110000001010000010000000011000000100000000100000000 ^
13
b1 7
b11100000110000001010000010000000011000000100000000100000000 -
b10000000000000000000000000000011 6
0/
#25000
1)
#30000
0)
b111100001110000011010000110000001011000010100000100100001000 *
b111100001110000011010000110000001011000010100000100100001000 9
b111100001110000011010000110000001011000010100000100100001000 ^
b111100001110000011010000110000001011000010100000100100001000 -
b1 5
b1 =
b1 a
#35000
1)
#40000
0)
b1011100010110000101010001010000010011000100100001000100010000 *
b1011100010110000101010001010000010011000100100001000100010000 9
b1011100010110000101010001010000010011000100100001000100010000 ^
b1011100010110000101010001010000010011000100100001000100010000 -
b10 5
b10 =
b10 a
#45000
1)
#50000
0)
b11000 *
b11000 9
b11000 ^
b11000 -
b11 5
b11 =
b11 a
#55000
1)
#60000
0)
03
b100 5
b100 =
b100 a
#65000
1)
#70000
1>
0)
10
#75000
b1 L
1N
1)
#80000
0)
#85000
0>
1Q
1!
1?
b10 L
b1 M
b1 `
b11111111 P
1@
b11100000110000001010000010000000011000000100000000100000000 A
b11100000110000001010000010000000011000000100000000100000000 R
b11100000110000001010000010000000011000000100000000100000000 b
b11100000110000001010000010000000011000000100000000100000000 f
1)
#90000
0)
#95000
0Y
b1000 \
b0 M
b0 `
0N
b111100001110000011010000110000001011000010100000100100001000 A
b111100001110000011010000110000001011000010100000100100001000 R
b111100001110000011010000110000001011000010100000100100001000 b
b111100001110000011010000110000001011000010100000100100001000 f
b1000 ]
1)
#100000
0)
#105000
0Q
b10000 \
b0 P
0@
b1000 ]
1)
#110000
0)
#115000
1)
#120000
0)
1+
00
#125000
b1 J
1I
1)
#130000
0)
#135000
1"
b1 [
b10 J
1)
#140000
0)
#145000
b11 J
b10 [
b1 #
b1 B
b1 X
1)
#150000
0)
#155000
b11 [
b10 #
b10 B
b10 X
b100 J
1)
#160000
0)
#165000
b101 J
b100 [
b11 #
b11 B
b11 X
1)
#170000
0)
#175000
b101 [
b100 #
b100 B
b100 X
b110 J
1)
#180000
0)
#185000
b111 J
b110 [
b101 #
b101 B
b101 X
1)
#190000
0)
#195000
b111 [
b110 #
b110 B
b110 X
b1000 J
1)
#200000
0)
#205000
b1001 J
b1000 [
b111 #
b111 B
b111 X
1)
#210000
0)
#215000
b1001 [
b1000 #
b1000 B
b1000 X
1K
0I
1)
#220000
0)
11
#225000
0K
b0 J
0"
b0 #
b0 B
b0 X
b0 [
1)
#230000
0)
01
#235000
b1 J
1I
1)
#240000
0)
#245000
b10 J
1"
b1 [
1)
#250000
0)
#255000
b10 [
b1 #
b1 B
b1 X
b11 J
1)
#260000
0)
#265000
b100 J
b11 [
b10 #
b10 B
b10 X
1)
#270000
0)
#275000
b100 [
b11 #
b11 B
b11 X
b101 J
1)
#280000
0)
#285000
b110 J
b101 [
b100 #
b100 B
b100 X
1)
#290000
0)
#295000
b110 [
b101 #
b101 B
b101 X
b111 J
1)
#300000
0)
#305000
b1000 J
b111 [
b110 #
b110 B
b110 X
1)
#310000
0)
#315000
b1000 [
b111 #
b111 B
b111 X
b1001 J
1)
#320000
0)
#325000
1K
0I
b1001 [
b1000 #
b1000 B
b1000 X
1)
#330000
0)
#335000
0"
b0 #
b0 B
b0 X
1)
