rtl/router/flash/sram.sv
module sram #(
    parameter int DEPTH = 64,
    parameter int DATA_WIDTH = 8,
    parameter int WRITE_WIDTH = 4,
    parameter int READ_WIDTH = 2,
    parameter int ADDR_WIDTH = $clog2(DEPTH * WRITE_WIDTH)
) (
    input logic i_clk, i_nrst, i_write_en, i_read_en,
    input logic [0:WRITE_WIDTH-1][DATA_WIDTH-1:0] i_data_in,
    input logic [ADDR_WIDTH-1:0] i_write_addr,
    input logic [0:READ_WIDTH-1][ADDR_WIDTH-1:0] i_read_addr, 
    output logic [0:READ_WIDTH-1][DATA_WIDTH-1:0] o_data_out
);
    logic [DATA_WIDTH-1:0] sram [0:(DEPTH * WRITE_WIDTH)-1];

    // Write takes precedence over read
    always_ff @(posedge i_clk or negedge i_nrst) begin
        if (!i_nrst) begin
            for (int i = 0; i < DEPTH * WRITE_WIDTH; i++) begin
                sram[i] <= '0;
            end
        end else begin
            if (i_write_en) begin
                for (int i = 0; i < WRITE_WIDTH; i++) begin
                    sram[i_write_addr + i] <= i_data_in[i];
                end
            end else if (i_read_en) begin
                for (int i = 0; i < READ_WIDTH; i++) begin
                    o_data_out[i] <= sram[i_read_addr[i]];
                end
            end
        end
    end
endmodule

rtl/router/flash/tb_sram.sv
module sram_rw_tb;

    // Parameters
    parameter int DEPTH = 64;
    parameter int DATA_WIDTH = 8;
    parameter int WRITE_WIDTH = 4;
    parameter int READ_WIDTH = 2;
    parameter int ADDR_WIDTH = $clog2(DEPTH * WRITE_WIDTH);
    parameter int INPUT_WIDTH = DATA_WIDTH * WRITE_WIDTH;
    parameter int OUTPUT_WIDTH = DATA_WIDTH * READ_WIDTH;

    // Inputs
    logic i_clk, i_nrst, i_write_en, i_read_en;
    logic [0:WRITE_WIDTH-1][DATA_WIDTH-1:0] i_data_in;
    logic [ADDR_WIDTH-1:0] i_write_addr;
    logic [0:READ_WIDTH-1][ADDR_WIDTH-1:0] i_read_addr;

    // Outputs
    logic [0:READ_WIDTH-1][DATA_WIDTH-1:0] o_data_out;

    // Instantiate the DUT
    sram #(
        .DEPTH(DEPTH),
        .DATA_WIDTH(DATA_WIDTH),
        .WRITE_WIDTH(WRITE_WIDTH),
        .READ_WIDTH(READ_WIDTH)
    ) dut (
        .i_clk(i_clk),
        .i_nrst(i_nrst),
        .i_write_en(i_write_en),
        .i_read_en(i_read_en),
        .i_data_in(i_data_in),
        .i_write_addr(i_write_addr),
        .i_read_addr(i_read_addr),
        .o_data_out(o_data_out)
    );

    // Clock generation
    initial begin
        i_clk = 0;
        forever #5 i_clk = ~i_clk; // Clock period = 10 ns
    end

    // Testbench logic
    initial begin
        // Initialize inputs
        i_nrst = 0;
        i_write_en = 0;
        i_read_en = 0;
        i_data_in = '{8'h00,8'h00,8'h00,8'h00}; // Initialize each element to 0
        i_write_addr = '0;
        i_read_addr = '{0,0}; // Initialize each address to 0

        // Apply reset
        #10 i_nrst = 1;

        // Perform a write operation
        #10 i_write_en = 1;
        i_write_addr = 0; // Start writing at address 10
        i_data_in = '{8'hA1, 8'hB2, 8'hC3, 8'hD4}; // 4 bytes of data
        #10 i_write_en = 0;

        // Perform a read operation
        #10 i_read_en = 1;
        i_read_addr = '{1, 0}; // Random addresses to read
        #10 i_read_en = 0;

        // Wait and finish
        #50 $finish;
    end

    // Dump waveforms
    initial begin
        $dumpfile("tb.vcd");
        $dumpvars;
    end

endmodule

rtl/router/flash/tb.vcd
$date
	Fri Dec 20 04:58:45 2024
$end
$version
	Icarus Verilog
$end
$timescale
	1s
$end
$scope module sram_rw_tb $end
$var wire 16 ! o_data_out [15:0] $end
$var parameter 32 " ADDR_WIDTH $end
$var parameter 32 # DATA_WIDTH $end
$var parameter 32 $ DEPTH $end
$var parameter 32 % INPUT_WIDTH $end
$var parameter 32 & OUTPUT_WIDTH $end
$var parameter 32 ' READ_WIDTH $end
$var parameter 32 ( WRITE_WIDTH $end
$var reg 1 ) i_clk $end
$var reg 32 * i_data_in [31:0] $end
$var reg 1 + i_nrst $end
$var reg 16 , i_read_addr [15:0] $end
$var reg 1 - i_read_en $end
$var reg 8 . i_write_addr [7:0] $end
$var reg 1 / i_write_en $end
$scope module dut $end
$var wire 1 ) i_clk $end
$var wire 32 0 i_data_in [31:0] $end
$var wire 1 + i_nrst $end
$var wire 16 1 i_read_addr [15:0] $end
$var wire 1 - i_read_en $end
$var wire 8 2 i_write_addr [7:0] $end
$var wire 1 / i_write_en $end
$var parameter 32 3 ADDR_WIDTH $end
$var parameter 32 4 DATA_WIDTH $end
$var parameter 32 5 DEPTH $end
$var parameter 32 6 READ_WIDTH $end
$var parameter 32 7 WRITE_WIDTH $end
$var reg 16 8 o_data_out [15:0] $end
$scope begin $ivl_for_loop0 $end
$var integer 32 9 i [31:0] $end
$upscope $end
$scope begin $ivl_for_loop1 $end
$var integer 32 : i [31:0] $end
$upscope $end
$scope begin $ivl_for_loop2 $end
$var integer 32 ; i [31:0] $end
$upscope $end
$upscope $end
$upscope $end
$enddefinitions $end
$comment Show the parameter values. $end
$dumpall
b100 7
b10 6
b1000000 5
b1000 4
b1000 3
b100 (
b10 '
b10000 &
b100000 %
b1000000 $
b1000 #
b1000 "
$end
#0
$dumpvars
b0 ;
b0 :
b100000000 9
bx 8
b0 2
b0 1
b0 0
0/
b0 .
0-
b0 ,
0+
b0 *
0)
bx !
$end
#5
b100000000 9
1)
#10
0)
1+
#15
1)
#20
0)
b10100001101100101100001111010100 *
b10100001101100101100001111010100 0
1/
#25
b100 :
1)
#30
0)
0/
#35
1)
#40
0)
b100000000 ,
b100000000 1
1-
#45
b1011001010100001 !
b1011001010100001 8
b10 ;
1)
#50
0)
0-
